ghupdate/__init__.py
ghupdate/controllers/__init__.py
ghupdate/controllers/base.py
ghupdate/controllers/updates.py
ghupdate/core/__init__.py
ghupdate/core/exc.py
ghupdate/core/version.py
ghupdate/ext/__init__.py
ghupdate/main.py
ghupdate/plugins/__init__.py
ghupdate-0.1.1.dist-info/LICENSE.md
ghupdate-0.1.1.dist-info/WHEEL
ghupdate-0.1.1.dist-info/METADATA
ghupdate-0.1.1.dist-info/RECORD
